{

    "id" : "CoolingBox10",
    
    "comment:devices" : "Register the list of devices to be controlled by the pidServer here. The dictionary key name represents the device controller instance. The dictionary value comprises the class name and its initial configuration.　Typically the configuration contains SPI/I2C pinouts, or USB device path, baud rate (for serial comm.) and readout calibration constants.",
	    
    "devices" : {
	"roomDP" : { "module"  : "InfluxAccess",
		     "class"   : "InfluxAccess",
		     "host" : "192.168.10.128",
		     "port" : 8086,
		     "database" : "pidDB",
		     "measurement" : "EnvMon",
		     "tags": {"sensor": "sht85_dp"},
		     "field" : "SHT85 DP"
		   },

	"roomTemp" : { "module"  : "InfluxAccess",
		       "class"   : "InfluxAccess",
		       "host" : "192.168.10.128",
		       "port" : 8086,
		       "database" : "pidDB",
		       "measurement" : "EnvMon",
		       "tags": {"sensor": "sht85_temp"},
		       "field" : "SHT85 Temp"
		   },

	"roomRH" : { "module"  : "InfluxAccess",
		     "class"   : "InfluxAccess",
		     "host" : "192.168.10.128",
		     "port" : 8086,
		     "database" : "pidDB",
		     "measurement" : "EnvMon",
		     "tags": {"sensor": "sht85_humi"},
		     "field" : "SHT85 RH"
		   },

	"peltierControl" : { "module"   : "PeltierControl",
			     "class"    : "TexioPFRControl",
			     "port"     : "/dev/Peltier", 
			     "address"  : 1,
			     "baud"     : 9600
			   },

        "dcsControl" : { "module" : "ArduinoSingleBoxDcsController",
			 "class"  : "ArduinoSingleBoxDcsController",
			 "port"   : "/dev/ttyUSB_ArduinoSingleBoxController",
			 "baud"   : 9600,
			 "useCalib": false
		       }
	
    },

    
    "comment:pidControl" : "object is the temperature to be controlled, and its name is specified as T_{keyname} where keyname is one of keys in sensorMap above.",
    
    "pidControl" : {
	"name"                  : "CoolingBox #21",
        "grafanaID"             : "76823a2c394b933c33a23a4ad94b3b89",
	"object"		: "T_module",
	"object_alt"            : "T_chuck",
	"minT"                  : -35.0,
	"maxT"                  : 30.0,
	"T_default"             : 25.0,
	"interval"		: 7.0,
	"interlockMargin"       : 5.0,
	"integralDuration"	: 10,
	"Pcontrol"		: 0.018,
	"Icontrol"		: 0.005,
	"Dcontrol"		: 3.00,
	"maxPfeedback"		: 0.80,
	"maxIfeedback"		: 0.05,
	"maxDfeedback"		: 0.60,
	"maxV"			: 9.4,
	"tOffsetP"		: 60.0,
	"tOffsetI"		: 180.0,
	"tOffsetD"		: 60.0,
	"LVip"			: "192.168.10.92",
	"LVch"			: "2",
	"LVtype"                : "CUSTOM",
    "LVOnCmd"               : "python3 /home/admin/titech_cool/pid/testLV.py on",
    "LVOffCmd"              : "python3 /home/admin/titech_cool/pid/testLV.py off",
    "LVIsOnCmd"             : "python3 /home/admin/titech_cool/pid/testLV.py status",
    "HVtype"                : "CUSTOM",
    "HVOnCmd"               : "python3 /home/admin/titech_cool/pid/testHV.py on",
    "HVOffCmd"              : "python3 /home/admin/titech_cool/pid/testHV.py off",
    "HVIsOnCmd"             : "python3 /home/admin/titech_cool/pid/testHV.py status"
    },
    
    "pidMonitor" : {
	    "maxHistory" : 300
    },

    
    "comment:stability" : "parameters to judge temperature stability.",
	    
    "stability" : {
	    "stabilityGaugingLength"  : 30,
	    "deviationTolerance"      : 0.75,
	    "Tstdev"                  : 0.50,
	    "Vstdev"                  : 0.40
    },

    
    "comment:influxDB" : "configuration of dcsDB recording. For the dictionary 'channels', keynames are parameter names stored in PidControl as data, while values are field names of the influxDB. The value names follow Shohei's convention.",
    
    "influxDB" : {
	    "database"    : "pidDB",
	    "hostname"    : "192.168.10.128",
	    "port"        : 8086,
	    "measurement" : "CoolingBox21"
    }
}
